clifx/__init__.py
clifx/__main__.py
clifx/__version__.py
clifx/lan.py
clifx/script.py
clifx-1.1.0rc0.dist-info/LICENSE
clifx-1.1.0rc0.dist-info/METADATA
clifx-1.1.0rc0.dist-info/WHEEL
clifx-1.1.0rc0.dist-info/entry_points.txt
clifx-1.1.0rc0.dist-info/RECORD
