Metadata-Version: 2.1
Name: clifx
Version: 1.1.0rc0
Summary: Cross-platform CLI for LIFX devices
License: MIT
Keywords: lifx,iot,cli,smarthome
Author: DrTexx
Author-email: 3269230-DrTexx@users.noreply.gitlab.com
Requires-Python: >=3.8,<4.0
Classifier: License :: OSI Approved :: MIT License
Classifier: Programming Language :: Python :: 3
Classifier: Programming Language :: Python :: 3.8
Classifier: Programming Language :: Python :: 3.9
Classifier: Programming Language :: Python :: 3.10
Classifier: Programming Language :: Python :: 3.11
Classifier: Programming Language :: Python :: 3
Requires-Dist: bitstring (<4)
Requires-Dist: click (>=8.1.3,<9.0.0)
Requires-Dist: lifxlan (>=1.2.7,<2.0.0)
